setup.py
cadc_iq_checker/__init__.py
cadc_iq_checker/catalog.py
cadc_iq_checker/cli.py
cadc_iq_checker/config.py
cadc_iq_checker/image_quality_model.py
cadc_iq_checker/storage.py
cadc_iq_checker.egg-info/PKG-INFO
cadc_iq_checker.egg-info/SOURCES.txt
cadc_iq_checker.egg-info/dependency_links.txt
cadc_iq_checker.egg-info/entry_points.txt
cadc_iq_checker.egg-info/requires.txt
cadc_iq_checker.egg-info/top_level.txt
cadc_iq_checker/config/default.nnw
cadc_iq_checker/config/default.param
cadc_iq_checker/config/default.sex
cadc_iq_checker/config/gauss_3.0_7x7.conv
cadc_iq_checker/config/xymfhe.sex
test/test_Megacam_Quality_Prediction.py