Metadata-Version: 1.0
Name: cadc-iq-checker
Version: 0.1
Summary: Image Quality Assessment AI
Home-page: UNKNOWN
Author: JJ Kavelaars
Author-email: JJ.Kavelaars@nrc-cnrc.gc.ca
License: MIT
Platform: UNKNOWN
